README.md
setup.py
kattis/__init__.py
kattis/__main__.py
kattis/auth.py
kattis/problems.py
kattis/user.py
kattis/utils.py
kattis.egg-info/PKG-INFO
kattis.egg-info/SOURCES.txt
kattis.egg-info/dependency_links.txt
kattis.egg-info/top_level.txt
samples/__init__.py
samples/main.py
test/__init__.py
test/test_auth.py
test/test_problem.py
test/test_problems.py
test/test_user_stats.py