Metadata-Version: 2.1
Name: kattis
Version: 1.0.0
Summary: A python wrapper for the Kattis API.
Home-page: https://github.com/terror/kattis-api
Author: Liam Scalzulli
Author-email: liam@scalzulli.com
License: UNKNOWN
Platform: UNKNOWN
Classifier: Programming Language :: Python :: 3
Classifier: License :: OSI Approved :: MIT License
Classifier: Operating System :: OS Independent
Requires-Python: >=3.6
